setup.py
frasco_forms/__init__.py
frasco_forms/form.py
frasco_forms/macros.html
frasco_forms.egg-info/PKG-INFO
frasco_forms.egg-info/SOURCES.txt
frasco_forms.egg-info/dependency_links.txt
frasco_forms.egg-info/not-zip-safe
frasco_forms.egg-info/requires.txt
frasco_forms.egg-info/top_level.txt