Metadata-Version: 1.0
Name: frasco-forms
Version: 0.2
Summary: WTForms integration for Frasco
Home-page: http://github.com/frascoweb/frasco-forms
Author: Maxime Bouroumeau-Fuseau
Author-email: maxime.bouroumeau@gmail.com
License: MIT
Platform: any
